<?xml version="1.0" encoding="utf-8"?>
<VBAudioVoicemeeterMacroButtonMap>
<MacroButtonConfiguration x0='62' y0='32' dx='770' dy='806' />
	<MacroButton index='1' type='0' color='5' key='0' ctrl='0' shift='0' alt='0' anyway='0' exclusive='0' trigger='0' xinput='0'>
		<MB_MIDI b1='91' b2='40' b3='40' b4='00' b5='00' b6='00' />
		<MB_TRIGGER tchannel='0' tin='0.0' tout='0.0' tmsHold='100' tafterMute='0' />
		<MB_XINPUT nctrl='0' nbutton='0' />
		<MB_Name>V / M</MB_Name>
		<MB_Subname>Toggle VFO/Memory</MB_Subname>
		<MB_InitRequest></MB_InitRequest>
		<MB_OnRequest>System.Execute("%USERPROFILE%\auto\v-m.cmd");</MB_OnRequest>
		<MB_OffRequest></MB_OffRequest>
	</MacroButton>
	<MacroButton index='2' type='0' color='5' key='0' ctrl='0' shift='0' alt='0' anyway='0' exclusive='0' trigger='0' xinput='0'>
		<MB_MIDI b1='00' b2='00' b3='00' b4='00' b5='00' b6='00' />
		<MB_TRIGGER tchannel='0' tin='0.0' tout='0.0' tmsHold='100' tafterMute='0' />
		<MB_XINPUT nctrl='0' nbutton='0' />
		<MB_Name>M => A</MB_Name>
		<MB_Subname>Memory to VFO A</MB_Subname>
		<MB_InitRequest></MB_InitRequest>
		<MB_OnRequest>System.Execute("%USERPROFILE%\auto\m-vfoa.cmd");</MB_OnRequest>
		<MB_OffRequest></MB_OffRequest>
	</MacroButton>
	<MacroButton index='3' type='0' color='5' key='0' ctrl='0' shift='0' alt='0' anyway='0' exclusive='0' trigger='0' xinput='0'>
		<MB_MIDI b1='00' b2='00' b3='00' b4='00' b5='00' b6='00' />
		<MB_TRIGGER tchannel='0' tin='0.0' tout='0.0' tmsHold='100' tafterMute='0' />
		<MB_XINPUT nctrl='0' nbutton='0' />
		<MB_Name>A = B</MB_Name>
		<MB_Subname></MB_Subname>
		<MB_InitRequest></MB_InitRequest>
		<MB_OnRequest>System.Execute("%USERPROFILE%\auto\a-to-b.cmd");</MB_OnRequest>
		<MB_OffRequest></MB_OffRequest>
	</MacroButton>
	<MacroButton index='4' type='0' color='5' key='0' ctrl='0' shift='0' alt='0' anyway='0' exclusive='0' trigger='0' xinput='0'>
		<MB_MIDI b1='00' b2='00' b3='00' b4='00' b5='00' b6='00' />
		<MB_TRIGGER tchannel='0' tin='0.0' tout='0.0' tmsHold='100' tafterMute='0' />
		<MB_XINPUT nctrl='0' nbutton='0' />
		<MB_Name>A / B</MB_Name>
		<MB_Subname>Toggle VFO A/B</MB_Subname>
		<MB_InitRequest></MB_InitRequest>
		<MB_OnRequest>System.Execute("%USERPROFILE%\auto\a-b.cmd");</MB_OnRequest>
		<MB_OffRequest></MB_OffRequest>
	</MacroButton>
	<MacroButton index='5' type='0' color='8' key='0' ctrl='0' shift='0' alt='0' anyway='0' exclusive='0' trigger='0' xinput='0'>
		<MB_MIDI b1='00' b2='00' b3='00' b4='00' b5='00' b6='00' />
		<MB_TRIGGER tchannel='0' tin='0.0' tout='0.0' tmsHold='100' tafterMute='0' />
		<MB_XINPUT nctrl='0' nbutton='0' />
		<MB_Name>RESET</MB_Name>
		<MB_Subname>Fix Digital Mode</MB_Subname>
		<MB_InitRequest>Strip[0].Gain="0";
Strip[0].A2=0;
Strip[0].B2=1;
Strip[1].A1=0;
Strip[1].Mute=1;
Strip[2].Gain="0";
Strip[3].Gain="0";
Strip[4].Gain="0";
Strip[4].A1=1;
Bus[0].Gain="0";
Bus[2].Gain="0";
Bus[3].Gain="0";
Bus[4].Gain="0";</MB_InitRequest>
		<MB_OnRequest>System.Execute("%USERPROFILE%\auto\fix-digital.cmd");</MB_OnRequest>
		<MB_OffRequest></MB_OffRequest>
	</MacroButton>
	<MacroButton index='6' type='0' color='0' key='0' ctrl='0' shift='0' alt='0' anyway='0' exclusive='0' trigger='0' xinput='0'>
		<MB_MIDI b1='00' b2='00' b3='00' b4='00' b5='00' b6='00' />
		<MB_TRIGGER tchannel='0' tin='0.0' tout='0.0' tmsHold='100' tafterMute='0' />
		<MB_XINPUT nctrl='0' nbutton='0' />
		<MB_Name></MB_Name>
		<MB_Subname></MB_Subname>
		<MB_InitRequest></MB_InitRequest>
		<MB_OnRequest></MB_OnRequest>
		<MB_OffRequest></MB_OffRequest>
	</MacroButton>
	<MacroButton index='7' type='0' color='0' key='0' ctrl='0' shift='0' alt='0' anyway='0' exclusive='0' trigger='0' xinput='0'>
		<MB_MIDI b1='00' b2='00' b3='00' b4='00' b5='00' b6='00' />
		<MB_TRIGGER tchannel='0' tin='0.0' tout='0.0' tmsHold='100' tafterMute='0' />
		<MB_XINPUT nctrl='0' nbutton='0' />
		<MB_Name></MB_Name>
		<MB_Subname></MB_Subname>
		<MB_InitRequest></MB_InitRequest>
		<MB_OnRequest>recorder.load="c:\audio\NINOCa.mp3";</MB_OnRequest>
		<MB_OffRequest></MB_OffRequest>
	</MacroButton>
	<MacroButton index='8' type='0' color='0' key='0' ctrl='0' shift='0' alt='0' anyway='0' exclusive='0' trigger='0' xinput='0'>
		<MB_MIDI b1='00' b2='00' b3='00' b4='00' b5='00' b6='00' />
		<MB_TRIGGER tchannel='0' tin='0.0' tout='0.0' tmsHold='100' tafterMute='0' />
		<MB_XINPUT nctrl='0' nbutton='0' />
		<MB_Name></MB_Name>
		<MB_Subname></MB_Subname>
		<MB_InitRequest></MB_InitRequest>
		<MB_OnRequest></MB_OnRequest>
		<MB_OffRequest></MB_OffRequest>
	</MacroButton>
	<MacroButton index='9' type='0' color='0' key='0' ctrl='0' shift='0' alt='0' anyway='0' exclusive='0' trigger='0' xinput='0'>
		<MB_MIDI b1='00' b2='00' b3='00' b4='00' b5='00' b6='00' />
		<MB_TRIGGER tchannel='0' tin='0.0' tout='0.0' tmsHold='100' tafterMute='0' />
		<MB_XINPUT nctrl='0' nbutton='0' />
		<MB_Name></MB_Name>
		<MB_Subname></MB_Subname>
		<MB_InitRequest></MB_InitRequest>
		<MB_OnRequest></MB_OnRequest>
		<MB_OffRequest></MB_OffRequest>
	</MacroButton>
	<MacroButton index='10' type='0' color='0' key='0' ctrl='0' shift='0' alt='0' anyway='0' exclusive='0' trigger='0' xinput='0'>
		<MB_MIDI b1='00' b2='00' b3='00' b4='00' b5='00' b6='00' />
		<MB_TRIGGER tchannel='0' tin='0.0' tout='0.0' tmsHold='100' tafterMute='0' />
		<MB_XINPUT nctrl='0' nbutton='0' />
		<MB_Name></MB_Name>
		<MB_Subname></MB_Subname>
		<MB_InitRequest></MB_InitRequest>
		<MB_OnRequest></MB_OnRequest>
		<MB_OffRequest></MB_OffRequest>
	</MacroButton>
	<MacroButton index='11' type='0' color='2' key='0' ctrl='0' shift='0' alt='0' anyway='0' exclusive='0' trigger='0' xinput='0'>
		<MB_MIDI b1='00' b2='00' b3='00' b4='00' b5='00' b6='00' />
		<MB_TRIGGER tchannel='0' tin='0.0' tout='0.0' tmsHold='100' tafterMute='0' />
		<MB_XINPUT nctrl='0' nbutton='0' />
		<MB_Name>CLAR -10</MB_Name>
		<MB_Subname>- 10 Hz Clar</MB_Subname>
		<MB_InitRequest></MB_InitRequest>
		<MB_OnRequest>System.Execute("%USERPROFILE%\auto\clar-down.cmd");</MB_OnRequest>
		<MB_OffRequest></MB_OffRequest>
	</MacroButton>
	<MacroButton index='12' type='1' color='2' key='0' ctrl='0' shift='0' alt='0' anyway='0' exclusive='0' trigger='0' xinput='0'>
		<MB_MIDI b1='00' b2='00' b3='00' b4='00' b5='00' b6='00' />
		<MB_TRIGGER tchannel='0' tin='0.0' tout='0.0' tmsHold='100' tafterMute='0' />
		<MB_XINPUT nctrl='0' nbutton='0' />
		<MB_Name>CLARIFIER</MB_Name>
		<MB_Subname></MB_Subname>
		<MB_InitRequest></MB_InitRequest>
		<MB_OnRequest>System.Execute("%USERPROFILE%\auto\clar-on.cmd");</MB_OnRequest>
		<MB_OffRequest>System.Execute("%USERPROFILE%\auto\clar-off.cmd");</MB_OffRequest>
	</MacroButton>
	<MacroButton index='13' type='0' color='2' key='0' ctrl='0' shift='0' alt='0' anyway='0' exclusive='0' trigger='0' xinput='0'>
		<MB_MIDI b1='00' b2='00' b3='00' b4='00' b5='00' b6='00' />
		<MB_TRIGGER tchannel='0' tin='0.0' tout='0.0' tmsHold='100' tafterMute='0' />
		<MB_XINPUT nctrl='0' nbutton='0' />
		<MB_Name>CLAR +10</MB_Name>
		<MB_Subname>+10 Hz Clar</MB_Subname>
		<MB_InitRequest></MB_InitRequest>
		<MB_OnRequest>System.Execute("%USERPROFILE%\auto\clar-up.cmd");</MB_OnRequest>
		<MB_OffRequest></MB_OffRequest>
	</MacroButton>
	<MacroButton index='14' type='0' color='2' key='0' ctrl='0' shift='0' alt='0' anyway='0' exclusive='0' trigger='0' xinput='0'>
		<MB_MIDI b1='00' b2='00' b3='00' b4='00' b5='00' b6='00' />
		<MB_TRIGGER tchannel='0' tin='0.0' tout='0.0' tmsHold='100' tafterMute='0' />
		<MB_XINPUT nctrl='0' nbutton='0' />
		<MB_Name>CLAR CLEAR</MB_Name>
		<MB_Subname>*Reset Clarifier</MB_Subname>
		<MB_InitRequest>Wait(100);
System.Execute("%USERPROFILE%\auto\clar-clear.cmd");</MB_InitRequest>
		<MB_OnRequest>System.Execute("%USERPROFILE%\auto\clar-clear.cmd");</MB_OnRequest>
		<MB_OffRequest></MB_OffRequest>
	</MacroButton>
	<MacroButton index='15' type='0' color='3' key='0' ctrl='0' shift='0' alt='0' anyway='0' exclusive='0' trigger='0' xinput='0'>
		<MB_MIDI b1='00' b2='00' b3='00' b4='00' b5='00' b6='00' />
		<MB_TRIGGER tchannel='0' tin='0.0' tout='0.0' tmsHold='100' tafterMute='0' />
		<MB_XINPUT nctrl='0' nbutton='0' />
		<MB_Name>MAIN MAP</MB_Name>
		<MB_Subname>Load Main Map</MB_Subname>
		<MB_InitRequest></MB_InitRequest>
		<MB_OnRequest>Strip[0].Gain="0";
Strip[0].A2=1;
Strip[0].B2=0;
Strip[1].A1=1;
Strip[1].Mute=0;
Strip[2].Gain="0";
Strip[3].Gain="0";
Strip[4].Gain="0";
Strip[4].A1=0;
Bus[0].Gain="0";
Bus[2].Gain="0";
Bus[3].Gain="0";
Bus[4].Gain="0";
Button(30).State = 0; //
Wait(50);
Button(31).State = 0; //
Wait(50);
Button(32).State = 0; //
Load("c:\users\rodrigo\auto\main-map.xml")</MB_OnRequest>
		<MB_OffRequest></MB_OffRequest>
	</MacroButton>
	<MacroButton index='16' type='0' color='0' key='0' ctrl='0' shift='0' alt='0' anyway='0' exclusive='0' trigger='0' xinput='0'>
		<MB_MIDI b1='00' b2='00' b3='00' b4='00' b5='00' b6='00' />
		<MB_TRIGGER tchannel='0' tin='0.0' tout='0.0' tmsHold='100' tafterMute='0' />
		<MB_XINPUT nctrl='0' nbutton='0' />
		<MB_Name></MB_Name>
		<MB_Subname></MB_Subname>
		<MB_InitRequest></MB_InitRequest>
		<MB_OnRequest></MB_OnRequest>
		<MB_OffRequest></MB_OffRequest>
	</MacroButton>
	<MacroButton index='17' type='0' color='0' key='0' ctrl='0' shift='0' alt='0' anyway='0' exclusive='0' trigger='0' xinput='0'>
		<MB_MIDI b1='00' b2='00' b3='00' b4='00' b5='00' b6='00' />
		<MB_TRIGGER tchannel='0' tin='0.0' tout='0.0' tmsHold='100' tafterMute='0' />
		<MB_XINPUT nctrl='0' nbutton='0' />
		<MB_Name></MB_Name>
		<MB_Subname></MB_Subname>
		<MB_InitRequest></MB_InitRequest>
		<MB_OnRequest>recorder.load="c:\audio\qrl.mp3";</MB_OnRequest>
		<MB_OffRequest></MB_OffRequest>
	</MacroButton>
	<MacroButton index='18' type='0' color='0' key='0' ctrl='0' shift='0' alt='0' anyway='0' exclusive='0' trigger='0' xinput='0'>
		<MB_MIDI b1='00' b2='00' b3='00' b4='00' b5='00' b6='00' />
		<MB_TRIGGER tchannel='0' tin='0.0' tout='0.0' tmsHold='100' tafterMute='0' />
		<MB_XINPUT nctrl='0' nbutton='0' />
		<MB_Name></MB_Name>
		<MB_Subname></MB_Subname>
		<MB_InitRequest></MB_InitRequest>
		<MB_OnRequest></MB_OnRequest>
		<MB_OffRequest></MB_OffRequest>
	</MacroButton>
	<MacroButton index='19' type='0' color='0' key='0' ctrl='0' shift='0' alt='0' anyway='0' exclusive='0' trigger='0' xinput='0'>
		<MB_MIDI b1='00' b2='00' b3='00' b4='00' b5='00' b6='00' />
		<MB_TRIGGER tchannel='0' tin='0.0' tout='0.0' tmsHold='100' tafterMute='0' />
		<MB_XINPUT nctrl='0' nbutton='0' />
		<MB_Name></MB_Name>
		<MB_Subname></MB_Subname>
		<MB_InitRequest></MB_InitRequest>
		<MB_OnRequest></MB_OnRequest>
		<MB_OffRequest></MB_OffRequest>
	</MacroButton>
	<MacroButton index='20' type='0' color='0' key='0' ctrl='0' shift='0' alt='0' anyway='0' exclusive='0' trigger='0' xinput='0'>
		<MB_MIDI b1='00' b2='00' b3='00' b4='00' b5='00' b6='00' />
		<MB_TRIGGER tchannel='0' tin='0.0' tout='0.0' tmsHold='100' tafterMute='0' />
		<MB_XINPUT nctrl='0' nbutton='0' />
		<MB_Name></MB_Name>
		<MB_Subname></MB_Subname>
		<MB_InitRequest></MB_InitRequest>
		<MB_OnRequest></MB_OnRequest>
		<MB_OffRequest></MB_OffRequest>
	</MacroButton>
	<MacroButton index='21' type='1' color='6' key='0' ctrl='0' shift='0' alt='0' anyway='0' exclusive='0' trigger='0' xinput='0'>
		<MB_MIDI b1='00' b2='00' b3='00' b4='00' b5='00' b6='00' />
		<MB_TRIGGER tchannel='0' tin='0.0' tout='0.0' tmsHold='100' tafterMute='0' />
		<MB_XINPUT nctrl='0' nbutton='0' />
		<MB_Name>MONITOR</MB_Name>
		<MB_Subname>TX Feedback</MB_Subname>
		<MB_InitRequest></MB_InitRequest>
		<MB_OnRequest>System.Execute("%USERPROFILE%\auto\moni-on.cmd");
Strip[0].A2=1;</MB_OnRequest>
		<MB_OffRequest>System.Execute("%USERPROFILE%\auto\moni-off.cmd");
Strip[0].A2=0;</MB_OffRequest>
	</MacroButton>
	<MacroButton index='22' type='1' color='6' key='0' ctrl='0' shift='0' alt='0' anyway='0' exclusive='0' trigger='0' xinput='0'>
		<MB_MIDI b1='90' b2='40' b3='40' b4='00' b5='00' b6='00' />
		<MB_TRIGGER tchannel='0' tin='0.0' tout='0.0' tmsHold='100' tafterMute='0' />
		<MB_XINPUT nctrl='0' nbutton='0' />
		<MB_Name>MONITOR SP</MB_Name>
		<MB_Subname>Output in Speakers</MB_Subname>
		<MB_InitRequest></MB_InitRequest>
		<MB_OnRequest>System.Execute("%USERPROFILE%\auto\moni-sp-on.cmd");</MB_OnRequest>
		<MB_OffRequest>System.Execute("%USERPROFILE%\auto\moni-sp-off.cmd");</MB_OffRequest>
	</MacroButton>
	<MacroButton index='23' type='1' color='7' key='0' ctrl='0' shift='0' alt='0' anyway='0' exclusive='0' trigger='0' xinput='0'>
		<MB_MIDI b1='00' b2='00' b3='00' b4='00' b5='00' b6='00' />
		<MB_TRIGGER tchannel='0' tin='0.0' tout='0.0' tmsHold='100' tafterMute='0' />
		<MB_XINPUT nctrl='0' nbutton='0' />
		<MB_Name>10 W</MB_Name>
		<MB_Subname>5 W</MB_Subname>
		<MB_InitRequest></MB_InitRequest>
		<MB_OnRequest>System.Execute("%USERPROFILE%\auto\10w.cmd");
Button(23).StateOnly = 0; // 40W
Button(24).StateOnly = 0; // 100W</MB_OnRequest>
		<MB_OffRequest>System.Execute("%USERPROFILE%\auto\5w.cmd");</MB_OffRequest>
	</MacroButton>
	<MacroButton index='24' type='1' color='7' key='0' ctrl='0' shift='0' alt='0' anyway='0' exclusive='0' trigger='0' xinput='0'>
		<MB_MIDI b1='00' b2='00' b3='00' b4='00' b5='00' b6='00' />
		<MB_TRIGGER tchannel='0' tin='0.0' tout='0.0' tmsHold='100' tafterMute='0' />
		<MB_XINPUT nctrl='0' nbutton='0' />
		<MB_Name>40 W</MB_Name>
		<MB_Subname>20 W</MB_Subname>
		<MB_InitRequest></MB_InitRequest>
		<MB_OnRequest>System.Execute("%USERPROFILE%\auto\40w.cmd");
Button(22).StateOnly = 0; // 40W
Button(24).StateOnly = 0; // 100W</MB_OnRequest>
		<MB_OffRequest>System.Execute("%USERPROFILE%\auto\20w.cmd");</MB_OffRequest>
	</MacroButton>
	<MacroButton index='25' type='1' color='7' key='0' ctrl='0' shift='0' alt='0' anyway='0' exclusive='0' trigger='0' xinput='0'>
		<MB_MIDI b1='00' b2='00' b3='00' b4='00' b5='00' b6='00' />
		<MB_TRIGGER tchannel='0' tin='0.0' tout='0.0' tmsHold='100' tafterMute='0' />
		<MB_XINPUT nctrl='0' nbutton='0' />
		<MB_Name>100 W</MB_Name>
		<MB_Subname>50 W</MB_Subname>
		<MB_InitRequest></MB_InitRequest>
		<MB_OnRequest>System.Execute("%USERPROFILE%\auto\100w.cmd");
Button(22).StateOnly = 0; // 40W
Button(23).StateOnly = 0; // 100W</MB_OnRequest>
		<MB_OffRequest>System.Execute("%USERPROFILE%\auto\50w.cmd");</MB_OffRequest>
	</MacroButton>
	<MacroButton index='26' type='1' color='0' key='0' ctrl='0' shift='0' alt='0' anyway='0' exclusive='0' trigger='0' xinput='0'>
		<MB_MIDI b1='00' b2='00' b3='00' b4='00' b5='00' b6='00' />
		<MB_TRIGGER tchannel='0' tin='0.0' tout='0.0' tmsHold='100' tafterMute='0' />
		<MB_XINPUT nctrl='0' nbutton='0' />
		<MB_Name></MB_Name>
		<MB_Subname></MB_Subname>
		<MB_InitRequest></MB_InitRequest>
		<MB_OnRequest></MB_OnRequest>
		<MB_OffRequest></MB_OffRequest>
	</MacroButton>
	<MacroButton index='27' type='0' color='0' key='0' ctrl='0' shift='0' alt='0' anyway='0' exclusive='0' trigger='0' xinput='0'>
		<MB_MIDI b1='00' b2='00' b3='00' b4='00' b5='00' b6='00' />
		<MB_TRIGGER tchannel='0' tin='0.0' tout='0.0' tmsHold='100' tafterMute='0' />
		<MB_XINPUT nctrl='0' nbutton='0' />
		<MB_Name></MB_Name>
		<MB_Subname></MB_Subname>
		<MB_InitRequest></MB_InitRequest>
		<MB_OnRequest></MB_OnRequest>
		<MB_OffRequest></MB_OffRequest>
	</MacroButton>
	<MacroButton index='28' type='0' color='0' key='0' ctrl='0' shift='0' alt='0' anyway='0' exclusive='0' trigger='0' xinput='0'>
		<MB_MIDI b1='00' b2='00' b3='00' b4='00' b5='00' b6='00' />
		<MB_TRIGGER tchannel='0' tin='0.0' tout='0.0' tmsHold='100' tafterMute='0' />
		<MB_XINPUT nctrl='0' nbutton='0' />
		<MB_Name></MB_Name>
		<MB_Subname></MB_Subname>
		<MB_InitRequest></MB_InitRequest>
		<MB_OnRequest></MB_OnRequest>
		<MB_OffRequest></MB_OffRequest>
	</MacroButton>
	<MacroButton index='29' type='0' color='0' key='0' ctrl='0' shift='0' alt='0' anyway='0' exclusive='0' trigger='0' xinput='0'>
		<MB_MIDI b1='00' b2='00' b3='00' b4='00' b5='00' b6='00' />
		<MB_TRIGGER tchannel='0' tin='0.0' tout='0.0' tmsHold='100' tafterMute='0' />
		<MB_XINPUT nctrl='0' nbutton='0' />
		<MB_Name></MB_Name>
		<MB_Subname></MB_Subname>
		<MB_InitRequest></MB_InitRequest>
		<MB_OnRequest></MB_OnRequest>
		<MB_OffRequest></MB_OffRequest>
	</MacroButton>
	<MacroButton index='30' type='0' color='0' key='0' ctrl='0' shift='0' alt='0' anyway='0' exclusive='0' trigger='0' xinput='0'>
		<MB_MIDI b1='00' b2='00' b3='00' b4='00' b5='00' b6='00' />
		<MB_TRIGGER tchannel='0' tin='0.0' tout='0.0' tmsHold='100' tafterMute='0' />
		<MB_XINPUT nctrl='0' nbutton='0' />
		<MB_Name></MB_Name>
		<MB_Subname></MB_Subname>
		<MB_InitRequest></MB_InitRequest>
		<MB_OnRequest></MB_OnRequest>
		<MB_OffRequest></MB_OffRequest>
	</MacroButton>
	<MacroButton index='31' type='1' color='0' key='0' ctrl='0' shift='0' alt='0' anyway='0' exclusive='1' trigger='0' xinput='0'>
		<MB_MIDI b1='00' b2='00' b3='00' b4='00' b5='00' b6='00' />
		<MB_TRIGGER tchannel='0' tin='0.0' tout='0.0' tmsHold='100' tafterMute='0' />
		<MB_XINPUT nctrl='0' nbutton='0' />
		<MB_Name>FT-8</MB_Name>
		<MB_Subname>MSHV</MB_Subname>
		<MB_InitRequest></MB_InitRequest>
		<MB_OnRequest>System.Execute("%USERPROFILE%\auto\ft8-on.cmd");
System.Execute("C:\ham\mshv\MSHV_WIN64.exe");
Wait(50);
Button(22).State = 1; // Flag up 10W
Button(31).StateOnly = 0; // RTTY
Button(32).StateOnly = 0; // SSTV</MB_OnRequest>
		<MB_OffRequest>System.Execute("%USERPROFILE%\auto\ft8-off.cmd");</MB_OffRequest>
	</MacroButton>
	<MacroButton index='32' type='1' color='0' key='0' ctrl='0' shift='0' alt='0' anyway='0' exclusive='0' trigger='0' xinput='0'>
		<MB_MIDI b1='00' b2='00' b3='00' b4='00' b5='00' b6='00' />
		<MB_TRIGGER tchannel='0' tin='0.0' tout='0.0' tmsHold='100' tafterMute='0' />
		<MB_XINPUT nctrl='0' nbutton='0' />
		<MB_Name>RTTY</MB_Name>
		<MB_Subname>MMTTY</MB_Subname>
		<MB_InitRequest></MB_InitRequest>
		<MB_OnRequest>System.Execute("%USERPROFILE%\auto\rtty-on.cmd");
System.Execute("C:\Ham\MMTTY\mmtty.exe");
Wait(50);
Button(22).State = 1; // Flag up 10W
Button(30).StateOnly = 0; // FT8
Button(32).StateOnly = 0; // SSTV</MB_OnRequest>
		<MB_OffRequest>System.Execute("%USERPROFILE%\auto\rtty-off.cmd");</MB_OffRequest>
	</MacroButton>
	<MacroButton index='33' type='1' color='0' key='0' ctrl='0' shift='0' alt='0' anyway='0' exclusive='0' trigger='0' xinput='0'>
		<MB_MIDI b1='00' b2='00' b3='00' b4='00' b5='00' b6='00' />
		<MB_TRIGGER tchannel='0' tin='0.0' tout='0.0' tmsHold='100' tafterMute='0' />
		<MB_XINPUT nctrl='0' nbutton='0' />
		<MB_Name>SSTV</MB_Name>
		<MB_Subname>MMSSTV</MB_Subname>
		<MB_InitRequest></MB_InitRequest>
		<MB_OnRequest>System.Execute("%USERPROFILE%\auto\sstv-on.cmd");
System.Execute("C:\Ham\MMSSTV\MMSSTV.EXE");
Wait(50);
Button(22).State = 1; // Flag up 10W
Button(31).StateOnly = 0; // RTTY
Button(30).StateOnly = 0; // FT8</MB_OnRequest>
		<MB_OffRequest>System.Execute("%USERPROFILE%\auto\sstv-off.cmd");</MB_OffRequest>
	</MacroButton>
	<MacroButton index='34' type='0' color='8' key='0' ctrl='0' shift='0' alt='0' anyway='0' exclusive='1' trigger='0' xinput='0'>
		<MB_MIDI b1='00' b2='00' b3='00' b4='00' b5='00' b6='00' />
		<MB_TRIGGER tchannel='0' tin='0.0' tout='0.0' tmsHold='100' tafterMute='0' />
		<MB_XINPUT nctrl='0' nbutton='0' />
		<MB_Name>BAND DOWN</MB_Name>
		<MB_Subname>( - )</MB_Subname>
		<MB_InitRequest></MB_InitRequest>
		<MB_OnRequest>System.Execute("%USERPROFILE%\auto\band-down.cmd");</MB_OnRequest>
		<MB_OffRequest></MB_OffRequest>
	</MacroButton>
	<MacroButton index='35' type='0' color='8' key='0' ctrl='0' shift='0' alt='0' anyway='0' exclusive='1' trigger='0' xinput='0'>
		<MB_MIDI b1='00' b2='00' b3='00' b4='00' b5='00' b6='00' />
		<MB_TRIGGER tchannel='0' tin='0.0' tout='0.0' tmsHold='100' tafterMute='0' />
		<MB_XINPUT nctrl='0' nbutton='0' />
		<MB_Name>BAND UP</MB_Name>
		<MB_Subname>( + )</MB_Subname>
		<MB_InitRequest></MB_InitRequest>
		<MB_OnRequest>System.Execute("%USERPROFILE%\auto\band-up.cmd");</MB_OnRequest>
		<MB_OffRequest></MB_OffRequest>
	</MacroButton>
	<MacroButton index='36' type='1' color='0' key='0' ctrl='0' shift='0' alt='0' anyway='0' exclusive='0' trigger='0' xinput='0'>
		<MB_MIDI b1='00' b2='00' b3='00' b4='00' b5='00' b6='00' />
		<MB_TRIGGER tchannel='0' tin='0.0' tout='0.0' tmsHold='100' tafterMute='0' />
		<MB_XINPUT nctrl='0' nbutton='0' />
		<MB_Name></MB_Name>
		<MB_Subname></MB_Subname>
		<MB_InitRequest></MB_InitRequest>
		<MB_OnRequest></MB_OnRequest>
		<MB_OffRequest></MB_OffRequest>
	</MacroButton>
	<MacroButton index='37' type='0' color='0' key='0' ctrl='0' shift='0' alt='0' anyway='0' exclusive='0' trigger='0' xinput='0'>
		<MB_MIDI b1='00' b2='00' b3='00' b4='00' b5='00' b6='00' />
		<MB_TRIGGER tchannel='0' tin='0.0' tout='0.0' tmsHold='100' tafterMute='0' />
		<MB_XINPUT nctrl='0' nbutton='0' />
		<MB_Name></MB_Name>
		<MB_Subname></MB_Subname>
		<MB_InitRequest></MB_InitRequest>
		<MB_OnRequest>recorder.load="c:\audio\cq\17.mp3";</MB_OnRequest>
		<MB_OffRequest></MB_OffRequest>
	</MacroButton>
	<MacroButton index='38' type='0' color='0' key='0' ctrl='0' shift='0' alt='0' anyway='0' exclusive='0' trigger='0' xinput='0'>
		<MB_MIDI b1='00' b2='00' b3='00' b4='00' b5='00' b6='00' />
		<MB_TRIGGER tchannel='0' tin='0.0' tout='0.0' tmsHold='100' tafterMute='0' />
		<MB_XINPUT nctrl='0' nbutton='0' />
		<MB_Name></MB_Name>
		<MB_Subname></MB_Subname>
		<MB_InitRequest></MB_InitRequest>
		<MB_OnRequest></MB_OnRequest>
		<MB_OffRequest></MB_OffRequest>
	</MacroButton>
	<MacroButton index='39' type='0' color='0' key='0' ctrl='0' shift='0' alt='0' anyway='0' exclusive='0' trigger='0' xinput='0'>
		<MB_MIDI b1='00' b2='00' b3='00' b4='00' b5='00' b6='00' />
		<MB_TRIGGER tchannel='0' tin='0.0' tout='0.0' tmsHold='100' tafterMute='0' />
		<MB_XINPUT nctrl='0' nbutton='0' />
		<MB_Name></MB_Name>
		<MB_Subname></MB_Subname>
		<MB_InitRequest></MB_InitRequest>
		<MB_OnRequest></MB_OnRequest>
		<MB_OffRequest></MB_OffRequest>
	</MacroButton>
	<MacroButton index='40' type='0' color='0' key='0' ctrl='0' shift='0' alt='0' anyway='0' exclusive='0' trigger='0' xinput='0'>
		<MB_MIDI b1='00' b2='00' b3='00' b4='00' b5='00' b6='00' />
		<MB_TRIGGER tchannel='0' tin='0.0' tout='0.0' tmsHold='100' tafterMute='0' />
		<MB_XINPUT nctrl='0' nbutton='0' />
		<MB_Name></MB_Name>
		<MB_Subname></MB_Subname>
		<MB_InitRequest></MB_InitRequest>
		<MB_OnRequest></MB_OnRequest>
		<MB_OffRequest></MB_OffRequest>
	</MacroButton>
	<MacroButton index='41' type='1' color='7' key='0' ctrl='0' shift='0' alt='0' anyway='0' exclusive='0' trigger='0' xinput='0'>
		<MB_MIDI b1='00' b2='00' b3='00' b4='00' b5='00' b6='00' />
		<MB_TRIGGER tchannel='0' tin='0.0' tout='0.0' tmsHold='100' tafterMute='0' />
		<MB_XINPUT nctrl='0' nbutton='0' />
		<MB_Name>+12 dB 10M</MB_Name>
		<MB_Subname></MB_Subname>
		<MB_InitRequest></MB_InitRequest>
		<MB_OnRequest>Strip[4].Gain="12";</MB_OnRequest>
		<MB_OffRequest>Strip[4].Gain="0";</MB_OffRequest>
	</MacroButton>
	<MacroButton index='42' type='0' color='3' key='0' ctrl='0' shift='0' alt='0' anyway='0' exclusive='0' trigger='0' xinput='0'>
		<MB_MIDI b1='00' b2='00' b3='00' b4='00' b5='00' b6='00' />
		<MB_TRIGGER tchannel='0' tin='0.0' tout='0.0' tmsHold='100' tafterMute='0' />
		<MB_XINPUT nctrl='0' nbutton='0' />
		<MB_Name>QMB FT8</MB_Name>
		<MB_Subname>15m/12m/10m/6m/2m</MB_Subname>
		<MB_InitRequest></MB_InitRequest>
		<MB_OnRequest>System.Execute("%USERPROFILE%\auto\qmb-digital.cmd");</MB_OnRequest>
		<MB_OffRequest></MB_OffRequest>
	</MacroButton>
	<MacroButton index='43' type='0' color='3' key='0' ctrl='0' shift='0' alt='0' anyway='0' exclusive='0' trigger='0' xinput='0'>
		<MB_MIDI b1='00' b2='00' b3='00' b4='00' b5='00' b6='00' />
		<MB_TRIGGER tchannel='0' tin='0.0' tout='0.0' tmsHold='100' tafterMute='0' />
		<MB_XINPUT nctrl='0' nbutton='0' />
		<MB_Name>60 M FT8</MB_Name>
		<MB_Subname>5 MHz Mem 03</MB_Subname>
		<MB_InitRequest></MB_InitRequest>
		<MB_OnRequest>System.Execute("%USERPROFILE%\auto\ft8-60m.cmd");</MB_OnRequest>
		<MB_OffRequest></MB_OffRequest>
	</MacroButton>
	<MacroButton index='44' type='0' color='1' key='0' ctrl='0' shift='0' alt='0' anyway='0' exclusive='0' trigger='0' xinput='0'>
		<MB_MIDI b1='00' b2='00' b3='00' b4='00' b5='00' b6='00' />
		<MB_TRIGGER tchannel='0' tin='0.0' tout='0.0' tmsHold='100' tafterMute='0' />
		<MB_XINPUT nctrl='0' nbutton='0' />
		<MB_Name>MULTI DOWN</MB_Name>
		<MB_Subname>( - )</MB_Subname>
		<MB_InitRequest></MB_InitRequest>
		<MB_OnRequest>System.Execute("%USERPROFILE%\auto\enc-down.cmd");</MB_OnRequest>
		<MB_OffRequest></MB_OffRequest>
	</MacroButton>
	<MacroButton index='45' type='0' color='1' key='0' ctrl='0' shift='0' alt='0' anyway='0' exclusive='0' trigger='0' xinput='0'>
		<MB_MIDI b1='00' b2='00' b3='00' b4='00' b5='00' b6='00' />
		<MB_TRIGGER tchannel='0' tin='0.0' tout='0.0' tmsHold='100' tafterMute='0' />
		<MB_XINPUT nctrl='0' nbutton='0' />
		<MB_Name>MULTI UP</MB_Name>
		<MB_Subname>( + )</MB_Subname>
		<MB_InitRequest></MB_InitRequest>
		<MB_OnRequest>System.Execute("%USERPROFILE%\auto\enc-up.cmd");</MB_OnRequest>
		<MB_OffRequest></MB_OffRequest>
	</MacroButton>
	<MacroButton index='46' type='1' color='0' key='0' ctrl='0' shift='0' alt='0' anyway='0' exclusive='0' trigger='0' xinput='0'>
		<MB_MIDI b1='00' b2='00' b3='00' b4='00' b5='00' b6='00' />
		<MB_TRIGGER tchannel='0' tin='0.0' tout='0.0' tmsHold='100' tafterMute='0' />
		<MB_XINPUT nctrl='0' nbutton='0' />
		<MB_Name></MB_Name>
		<MB_Subname></MB_Subname>
		<MB_InitRequest></MB_InitRequest>
		<MB_OnRequest></MB_OnRequest>
		<MB_OffRequest></MB_OffRequest>
	</MacroButton>
	<MacroButton index='47' type='0' color='0' key='0' ctrl='0' shift='0' alt='0' anyway='0' exclusive='0' trigger='0' xinput='0'>
		<MB_MIDI b1='00' b2='00' b3='00' b4='00' b5='00' b6='00' />
		<MB_TRIGGER tchannel='0' tin='0.0' tout='0.0' tmsHold='100' tafterMute='0' />
		<MB_XINPUT nctrl='0' nbutton='0' />
		<MB_Name></MB_Name>
		<MB_Subname></MB_Subname>
		<MB_InitRequest></MB_InitRequest>
		<MB_OnRequest>recorder.load="c:\audio\cq\15.mp3";</MB_OnRequest>
		<MB_OffRequest></MB_OffRequest>
	</MacroButton>
	<MacroButton index='48' type='0' color='0' key='0' ctrl='0' shift='0' alt='0' anyway='0' exclusive='0' trigger='0' xinput='0'>
		<MB_MIDI b1='00' b2='00' b3='00' b4='00' b5='00' b6='00' />
		<MB_TRIGGER tchannel='0' tin='0.0' tout='0.0' tmsHold='100' tafterMute='0' />
		<MB_XINPUT nctrl='0' nbutton='0' />
		<MB_Name></MB_Name>
		<MB_Subname></MB_Subname>
		<MB_InitRequest></MB_InitRequest>
		<MB_OnRequest>recorder.load="c:\audio\cq\15.mp3";</MB_OnRequest>
		<MB_OffRequest></MB_OffRequest>
	</MacroButton>
	<MacroButton index='49' type='0' color='0' key='0' ctrl='0' shift='0' alt='0' anyway='0' exclusive='0' trigger='0' xinput='0'>
		<MB_MIDI b1='00' b2='00' b3='00' b4='00' b5='00' b6='00' />
		<MB_TRIGGER tchannel='0' tin='0.0' tout='0.0' tmsHold='100' tafterMute='0' />
		<MB_XINPUT nctrl='0' nbutton='0' />
		<MB_Name></MB_Name>
		<MB_Subname></MB_Subname>
		<MB_InitRequest></MB_InitRequest>
		<MB_OnRequest></MB_OnRequest>
		<MB_OffRequest></MB_OffRequest>
	</MacroButton>
	<MacroButton index='50' type='0' color='0' key='0' ctrl='0' shift='0' alt='0' anyway='0' exclusive='0' trigger='0' xinput='0'>
		<MB_MIDI b1='00' b2='00' b3='00' b4='00' b5='00' b6='00' />
		<MB_TRIGGER tchannel='0' tin='0.0' tout='0.0' tmsHold='100' tafterMute='0' />
		<MB_XINPUT nctrl='0' nbutton='0' />
		<MB_Name></MB_Name>
		<MB_Subname></MB_Subname>
		<MB_InitRequest></MB_InitRequest>
		<MB_OnRequest></MB_OnRequest>
		<MB_OffRequest></MB_OffRequest>
	</MacroButton>
	<MacroButton index='51' type='1' color='4' key='0' ctrl='0' shift='0' alt='0' anyway='0' exclusive='0' trigger='0' xinput='0'>
		<MB_MIDI b1='00' b2='00' b3='00' b4='00' b5='00' b6='00' />
		<MB_TRIGGER tchannel='0' tin='0.0' tout='0.0' tmsHold='100' tafterMute='0' />
		<MB_XINPUT nctrl='0' nbutton='0' />
		<MB_Name>NARROW</MB_Name>
		<MB_Subname>350 Hz Wide</MB_Subname>
		<MB_InitRequest></MB_InitRequest>
		<MB_OnRequest>System.Execute("%USERPROFILE%\auto\digital-narrow.cmd");</MB_OnRequest>
		<MB_OffRequest>System.Execute("%USERPROFILE%\auto\digital-wide.cmd");</MB_OffRequest>
	</MacroButton>
	<MacroButton index='52' type='1' color='0' key='0' ctrl='0' shift='0' alt='0' anyway='0' exclusive='0' trigger='0' xinput='0'>
		<MB_MIDI b1='00' b2='00' b3='00' b4='00' b5='00' b6='00' />
		<MB_TRIGGER tchannel='0' tin='0.0' tout='0.0' tmsHold='100' tafterMute='0' />
		<MB_XINPUT nctrl='0' nbutton='0' />
		<MB_Name></MB_Name>
		<MB_Subname></MB_Subname>
		<MB_InitRequest></MB_InitRequest>
		<MB_OnRequest></MB_OnRequest>
		<MB_OffRequest>
</MB_OffRequest>
	</MacroButton>
	<MacroButton index='53' type='1' color='4' key='0' ctrl='0' shift='0' alt='0' anyway='0' exclusive='0' trigger='0' xinput='0'>
		<MB_MIDI b1='00' b2='00' b3='00' b4='00' b5='00' b6='00' />
		<MB_TRIGGER tchannel='0' tin='0.0' tout='0.0' tmsHold='100' tafterMute='0' />
		<MB_XINPUT nctrl='0' nbutton='0' />
		<MB_Name>NOTCH</MB_Name>
		<MB_Subname>On / Off</MB_Subname>
		<MB_InitRequest></MB_InitRequest>
		<MB_OnRequest>System.Execute("%USERPROFILE%\auto\notch-on.cmd");</MB_OnRequest>
		<MB_OffRequest>System.Execute("%USERPROFILE%\auto\notch-off.cmd");</MB_OffRequest>
	</MacroButton>
	<MacroButton index='54' type='1' color='6' key='0' ctrl='0' shift='0' alt='0' anyway='0' exclusive='0' trigger='0' xinput='0'>
		<MB_MIDI b1='00' b2='00' b3='00' b4='00' b5='00' b6='00' />
		<MB_TRIGGER tchannel='0' tin='0.0' tout='0.0' tmsHold='100' tafterMute='0' />
		<MB_XINPUT nctrl='0' nbutton='0' />
		<MB_Name>ATT</MB_Name>
		<MB_Subname>Attenuator -12 dB</MB_Subname>
		<MB_InitRequest></MB_InitRequest>
		<MB_OnRequest>System.Execute("%USERPROFILE%\auto\att-on.cmd");
Wait(100);
Button(54).State = 0; // AMP</MB_OnRequest>
		<MB_OffRequest>System.Execute("%USERPROFILE%\auto\att-off.cmd");</MB_OffRequest>
	</MacroButton>
	<MacroButton index='55' type='1' color='6' key='0' ctrl='0' shift='0' alt='0' anyway='0' exclusive='0' trigger='0' xinput='0'>
		<MB_MIDI b1='00' b2='00' b3='00' b4='00' b5='00' b6='00' />
		<MB_TRIGGER tchannel='0' tin='0.0' tout='0.0' tmsHold='100' tafterMute='0' />
		<MB_XINPUT nctrl='0' nbutton='0' />
		<MB_Name>PREAMP</MB_Name>
		<MB_Subname>+12 dB Amplifier</MB_Subname>
		<MB_InitRequest></MB_InitRequest>
		<MB_OnRequest>System.Execute("%USERPROFILE%\auto\amp-amp1.cmd");
Wait(100);
Button(53).State = 0; // ATT</MB_OnRequest>
		<MB_OffRequest>System.Execute("%USERPROFILE%\auto\amp-ipo.cmd");</MB_OffRequest>
	</MacroButton>
	<MacroButton index='56' type='0' color='0' key='0' ctrl='0' shift='0' alt='0' anyway='0' exclusive='0' trigger='0' xinput='0'>
		<MB_MIDI b1='00' b2='00' b3='00' b4='00' b5='00' b6='00' />
		<MB_TRIGGER tchannel='0' tin='0.0' tout='0.0' tmsHold='100' tafterMute='0' />
		<MB_XINPUT nctrl='0' nbutton='0' />
		<MB_Name></MB_Name>
		<MB_Subname></MB_Subname>
		<MB_InitRequest></MB_InitRequest>
		<MB_OnRequest></MB_OnRequest>
		<MB_OffRequest></MB_OffRequest>
	</MacroButton>
	<MacroButton index='57' type='0' color='0' key='0' ctrl='0' shift='0' alt='0' anyway='0' exclusive='0' trigger='0' xinput='0'>
		<MB_MIDI b1='00' b2='00' b3='00' b4='00' b5='00' b6='00' />
		<MB_TRIGGER tchannel='0' tin='0.0' tout='0.0' tmsHold='100' tafterMute='0' />
		<MB_XINPUT nctrl='0' nbutton='0' />
		<MB_Name></MB_Name>
		<MB_Subname></MB_Subname>
		<MB_InitRequest></MB_InitRequest>
		<MB_OnRequest>recorder.load="c:\audio\cq\12.mp3";</MB_OnRequest>
		<MB_OffRequest></MB_OffRequest>
	</MacroButton>
	<MacroButton index='58' type='0' color='0' key='0' ctrl='0' shift='0' alt='0' anyway='0' exclusive='0' trigger='0' xinput='0'>
		<MB_MIDI b1='00' b2='00' b3='00' b4='00' b5='00' b6='00' />
		<MB_TRIGGER tchannel='0' tin='0.0' tout='0.0' tmsHold='100' tafterMute='0' />
		<MB_XINPUT nctrl='0' nbutton='0' />
		<MB_Name></MB_Name>
		<MB_Subname></MB_Subname>
		<MB_InitRequest></MB_InitRequest>
		<MB_OnRequest></MB_OnRequest>
		<MB_OffRequest></MB_OffRequest>
	</MacroButton>
	<MacroButton index='59' type='0' color='0' key='0' ctrl='0' shift='0' alt='0' anyway='0' exclusive='0' trigger='0' xinput='0'>
		<MB_MIDI b1='00' b2='00' b3='00' b4='00' b5='00' b6='00' />
		<MB_TRIGGER tchannel='0' tin='0.0' tout='0.0' tmsHold='100' tafterMute='0' />
		<MB_XINPUT nctrl='0' nbutton='0' />
		<MB_Name></MB_Name>
		<MB_Subname></MB_Subname>
		<MB_InitRequest></MB_InitRequest>
		<MB_OnRequest></MB_OnRequest>
		<MB_OffRequest></MB_OffRequest>
	</MacroButton>
	<MacroButton index='60' type='0' color='0' key='0' ctrl='0' shift='0' alt='0' anyway='0' exclusive='0' trigger='0' xinput='0'>
		<MB_MIDI b1='00' b2='00' b3='00' b4='00' b5='00' b6='00' />
		<MB_TRIGGER tchannel='0' tin='0.0' tout='0.0' tmsHold='100' tafterMute='0' />
		<MB_XINPUT nctrl='0' nbutton='0' />
		<MB_Name></MB_Name>
		<MB_Subname></MB_Subname>
		<MB_InitRequest></MB_InitRequest>
		<MB_OnRequest></MB_OnRequest>
		<MB_OffRequest></MB_OffRequest>
	</MacroButton>
	<MacroButton index='61' type='1' color='0' key='0' ctrl='0' shift='0' alt='0' anyway='0' exclusive='0' trigger='0' xinput='0'>
		<MB_MIDI b1='00' b2='00' b3='00' b4='00' b5='00' b6='00' />
		<MB_TRIGGER tchannel='0' tin='0.0' tout='0.0' tmsHold='100' tafterMute='0' />
		<MB_XINPUT nctrl='0' nbutton='0' />
		<MB_Name></MB_Name>
		<MB_Subname></MB_Subname>
		<MB_InitRequest></MB_InitRequest>
		<MB_OnRequest></MB_OnRequest>
		<MB_OffRequest></MB_OffRequest>
	</MacroButton>
	<MacroButton index='62' type='1' color='0' key='0' ctrl='0' shift='0' alt='0' anyway='0' exclusive='0' trigger='0' xinput='0'>
		<MB_MIDI b1='00' b2='00' b3='00' b4='00' b5='00' b6='00' />
		<MB_TRIGGER tchannel='0' tin='0.0' tout='0.0' tmsHold='100' tafterMute='0' />
		<MB_XINPUT nctrl='0' nbutton='0' />
		<MB_Name></MB_Name>
		<MB_Subname></MB_Subname>
		<MB_InitRequest></MB_InitRequest>
		<MB_OnRequest></MB_OnRequest>
		<MB_OffRequest></MB_OffRequest>
	</MacroButton>
	<MacroButton index='63' type='1' color='0' key='0' ctrl='0' shift='0' alt='0' anyway='0' exclusive='0' trigger='0' xinput='0'>
		<MB_MIDI b1='00' b2='00' b3='00' b4='00' b5='00' b6='00' />
		<MB_TRIGGER tchannel='0' tin='0.0' tout='0.0' tmsHold='100' tafterMute='0' />
		<MB_XINPUT nctrl='0' nbutton='0' />
		<MB_Name></MB_Name>
		<MB_Subname></MB_Subname>
		<MB_InitRequest></MB_InitRequest>
		<MB_OnRequest></MB_OnRequest>
		<MB_OffRequest></MB_OffRequest>
	</MacroButton>
	<MacroButton index='64' type='1' color='0' key='0' ctrl='0' shift='0' alt='0' anyway='0' exclusive='0' trigger='0' xinput='0'>
		<MB_MIDI b1='00' b2='00' b3='00' b4='00' b5='00' b6='00' />
		<MB_TRIGGER tchannel='0' tin='0.0' tout='0.0' tmsHold='100' tafterMute='0' />
		<MB_XINPUT nctrl='0' nbutton='0' />
		<MB_Name></MB_Name>
		<MB_Subname></MB_Subname>
		<MB_InitRequest></MB_InitRequest>
		<MB_OnRequest></MB_OnRequest>
		<MB_OffRequest></MB_OffRequest>
	</MacroButton>
	<MacroButton index='65' type='1' color='0' key='0' ctrl='0' shift='0' alt='0' anyway='0' exclusive='0' trigger='0' xinput='0'>
		<MB_MIDI b1='00' b2='00' b3='00' b4='00' b5='00' b6='00' />
		<MB_TRIGGER tchannel='0' tin='0.0' tout='0.0' tmsHold='100' tafterMute='0' />
		<MB_XINPUT nctrl='0' nbutton='0' />
		<MB_Name></MB_Name>
		<MB_Subname></MB_Subname>
		<MB_InitRequest></MB_InitRequest>
		<MB_OnRequest></MB_OnRequest>
		<MB_OffRequest></MB_OffRequest>
	</MacroButton>
	<MacroButton index='66' type='0' color='0' key='0' ctrl='0' shift='0' alt='0' anyway='0' exclusive='0' trigger='0' xinput='0'>
		<MB_MIDI b1='00' b2='00' b3='00' b4='00' b5='00' b6='00' />
		<MB_TRIGGER tchannel='0' tin='0.0' tout='0.0' tmsHold='100' tafterMute='0' />
		<MB_XINPUT nctrl='0' nbutton='0' />
		<MB_Name></MB_Name>
		<MB_Subname></MB_Subname>
		<MB_InitRequest></MB_InitRequest>
		<MB_OnRequest></MB_OnRequest>
		<MB_OffRequest></MB_OffRequest>
	</MacroButton>
	<MacroButton index='67' type='0' color='0' key='0' ctrl='0' shift='0' alt='0' anyway='0' exclusive='0' trigger='0' xinput='0'>
		<MB_MIDI b1='00' b2='00' b3='00' b4='00' b5='00' b6='00' />
		<MB_TRIGGER tchannel='0' tin='0.0' tout='0.0' tmsHold='100' tafterMute='0' />
		<MB_XINPUT nctrl='0' nbutton='0' />
		<MB_Name></MB_Name>
		<MB_Subname></MB_Subname>
		<MB_InitRequest></MB_InitRequest>
		<MB_OnRequest></MB_OnRequest>
		<MB_OffRequest></MB_OffRequest>
	</MacroButton>
	<MacroButton index='68' type='0' color='0' key='0' ctrl='0' shift='0' alt='0' anyway='0' exclusive='0' trigger='0' xinput='0'>
		<MB_MIDI b1='00' b2='00' b3='00' b4='00' b5='00' b6='00' />
		<MB_TRIGGER tchannel='0' tin='0.0' tout='0.0' tmsHold='100' tafterMute='0' />
		<MB_XINPUT nctrl='0' nbutton='0' />
		<MB_Name></MB_Name>
		<MB_Subname></MB_Subname>
		<MB_InitRequest></MB_InitRequest>
		<MB_OnRequest></MB_OnRequest>
		<MB_OffRequest></MB_OffRequest>
	</MacroButton>
	<MacroButton index='69' type='0' color='0' key='0' ctrl='0' shift='0' alt='0' anyway='0' exclusive='0' trigger='0' xinput='0'>
		<MB_MIDI b1='00' b2='00' b3='00' b4='00' b5='00' b6='00' />
		<MB_TRIGGER tchannel='0' tin='0.0' tout='0.0' tmsHold='100' tafterMute='0' />
		<MB_XINPUT nctrl='0' nbutton='0' />
		<MB_Name></MB_Name>
		<MB_Subname></MB_Subname>
		<MB_InitRequest></MB_InitRequest>
		<MB_OnRequest></MB_OnRequest>
		<MB_OffRequest></MB_OffRequest>
	</MacroButton>
	<MacroButton index='70' type='0' color='0' key='0' ctrl='0' shift='0' alt='0' anyway='0' exclusive='0' trigger='0' xinput='0'>
		<MB_MIDI b1='00' b2='00' b3='00' b4='00' b5='00' b6='00' />
		<MB_TRIGGER tchannel='0' tin='0.0' tout='0.0' tmsHold='100' tafterMute='0' />
		<MB_XINPUT nctrl='0' nbutton='0' />
		<MB_Name></MB_Name>
		<MB_Subname></MB_Subname>
		<MB_InitRequest></MB_InitRequest>
		<MB_OnRequest></MB_OnRequest>
		<MB_OffRequest></MB_OffRequest>
	</MacroButton>
	<MacroButton index='71' type='0' color='0' key='0' ctrl='0' shift='0' alt='0' anyway='0' exclusive='0' trigger='0' xinput='0'>
		<MB_MIDI b1='00' b2='00' b3='00' b4='00' b5='00' b6='00' />
		<MB_TRIGGER tchannel='0' tin='0.0' tout='0.0' tmsHold='100' tafterMute='0' />
		<MB_XINPUT nctrl='0' nbutton='0' />
		<MB_Name></MB_Name>
		<MB_Subname></MB_Subname>
		<MB_InitRequest></MB_InitRequest>
		<MB_OnRequest></MB_OnRequest>
		<MB_OffRequest></MB_OffRequest>
	</MacroButton>
	<MacroButton index='72' type='0' color='0' key='0' ctrl='0' shift='0' alt='0' anyway='0' exclusive='0' trigger='0' xinput='0'>
		<MB_MIDI b1='00' b2='00' b3='00' b4='00' b5='00' b6='00' />
		<MB_TRIGGER tchannel='0' tin='0.0' tout='0.0' tmsHold='100' tafterMute='0' />
		<MB_XINPUT nctrl='0' nbutton='0' />
		<MB_Name></MB_Name>
		<MB_Subname></MB_Subname>
		<MB_InitRequest></MB_InitRequest>
		<MB_OnRequest></MB_OnRequest>
		<MB_OffRequest></MB_OffRequest>
	</MacroButton>
	<MacroButton index='73' type='0' color='0' key='0' ctrl='0' shift='0' alt='0' anyway='0' exclusive='0' trigger='0' xinput='0'>
		<MB_MIDI b1='00' b2='00' b3='00' b4='00' b5='00' b6='00' />
		<MB_TRIGGER tchannel='0' tin='0.0' tout='0.0' tmsHold='100' tafterMute='0' />
		<MB_XINPUT nctrl='0' nbutton='0' />
		<MB_Name></MB_Name>
		<MB_Subname></MB_Subname>
		<MB_InitRequest></MB_InitRequest>
		<MB_OnRequest></MB_OnRequest>
		<MB_OffRequest></MB_OffRequest>
	</MacroButton>
	<MacroButton index='74' type='0' color='0' key='0' ctrl='0' shift='0' alt='0' anyway='0' exclusive='0' trigger='0' xinput='0'>
		<MB_MIDI b1='00' b2='00' b3='00' b4='00' b5='00' b6='00' />
		<MB_TRIGGER tchannel='0' tin='0.0' tout='0.0' tmsHold='100' tafterMute='0' />
		<MB_XINPUT nctrl='0' nbutton='0' />
		<MB_Name></MB_Name>
		<MB_Subname></MB_Subname>
		<MB_InitRequest></MB_InitRequest>
		<MB_OnRequest></MB_OnRequest>
		<MB_OffRequest></MB_OffRequest>
	</MacroButton>
	<MacroButton index='75' type='0' color='0' key='0' ctrl='0' shift='0' alt='0' anyway='0' exclusive='0' trigger='0' xinput='0'>
		<MB_MIDI b1='00' b2='00' b3='00' b4='00' b5='00' b6='00' />
		<MB_TRIGGER tchannel='0' tin='0.0' tout='0.0' tmsHold='100' tafterMute='0' />
		<MB_XINPUT nctrl='0' nbutton='0' />
		<MB_Name></MB_Name>
		<MB_Subname></MB_Subname>
		<MB_InitRequest></MB_InitRequest>
		<MB_OnRequest></MB_OnRequest>
		<MB_OffRequest></MB_OffRequest>
	</MacroButton>
	<MacroButton index='76' type='0' color='0' key='0' ctrl='0' shift='0' alt='0' anyway='0' exclusive='0' trigger='0' xinput='0'>
		<MB_MIDI b1='00' b2='00' b3='00' b4='00' b5='00' b6='00' />
		<MB_TRIGGER tchannel='0' tin='0.0' tout='0.0' tmsHold='100' tafterMute='0' />
		<MB_XINPUT nctrl='0' nbutton='0' />
		<MB_Name></MB_Name>
		<MB_Subname></MB_Subname>
		<MB_InitRequest></MB_InitRequest>
		<MB_OnRequest></MB_OnRequest>
		<MB_OffRequest></MB_OffRequest>
	</MacroButton>
	<MacroButton index='77' type='0' color='0' key='0' ctrl='0' shift='0' alt='0' anyway='0' exclusive='0' trigger='0' xinput='0'>
		<MB_MIDI b1='00' b2='00' b3='00' b4='00' b5='00' b6='00' />
		<MB_TRIGGER tchannel='0' tin='0.0' tout='0.0' tmsHold='100' tafterMute='0' />
		<MB_XINPUT nctrl='0' nbutton='0' />
		<MB_Name></MB_Name>
		<MB_Subname></MB_Subname>
		<MB_InitRequest></MB_InitRequest>
		<MB_OnRequest></MB_OnRequest>
		<MB_OffRequest></MB_OffRequest>
	</MacroButton>
	<MacroButton index='78' type='0' color='0' key='0' ctrl='0' shift='0' alt='0' anyway='0' exclusive='0' trigger='0' xinput='0'>
		<MB_MIDI b1='00' b2='00' b3='00' b4='00' b5='00' b6='00' />
		<MB_TRIGGER tchannel='0' tin='0.0' tout='0.0' tmsHold='100' tafterMute='0' />
		<MB_XINPUT nctrl='0' nbutton='0' />
		<MB_Name></MB_Name>
		<MB_Subname></MB_Subname>
		<MB_InitRequest></MB_InitRequest>
		<MB_OnRequest></MB_OnRequest>
		<MB_OffRequest></MB_OffRequest>
	</MacroButton>
	<MacroButton index='79' type='0' color='0' key='0' ctrl='0' shift='0' alt='0' anyway='0' exclusive='0' trigger='0' xinput='0'>
		<MB_MIDI b1='00' b2='00' b3='00' b4='00' b5='00' b6='00' />
		<MB_TRIGGER tchannel='0' tin='0.0' tout='0.0' tmsHold='100' tafterMute='0' />
		<MB_XINPUT nctrl='0' nbutton='0' />
		<MB_Name></MB_Name>
		<MB_Subname></MB_Subname>
		<MB_InitRequest></MB_InitRequest>
		<MB_OnRequest></MB_OnRequest>
		<MB_OffRequest></MB_OffRequest>
	</MacroButton>
	<MacroButton index='80' type='0' color='0' key='0' ctrl='0' shift='0' alt='0' anyway='0' exclusive='0' trigger='0' xinput='0'>
		<MB_MIDI b1='00' b2='00' b3='00' b4='00' b5='00' b6='00' />
		<MB_TRIGGER tchannel='0' tin='0.0' tout='0.0' tmsHold='100' tafterMute='0' />
		<MB_XINPUT nctrl='0' nbutton='0' />
		<MB_Name></MB_Name>
		<MB_Subname></MB_Subname>
		<MB_InitRequest></MB_InitRequest>
		<MB_OnRequest></MB_OnRequest>
		<MB_OffRequest></MB_OffRequest>
	</MacroButton>
</MacroButtonConfiguration>
</VBAudioVoicemeeterMacroButtonMap>
